tombolenkovac/__main__.py
tombolenkovac/draw.py
tombolenkovac/generate.py
tombolenkovac/main.py
tombolenkovac/tags.py
tombolenkovac/data/logo.png
tombolenkovac-0.2.4.dist-info/LICENSE
tombolenkovac-0.2.4.dist-info/METADATA
tombolenkovac-0.2.4.dist-info/WHEEL
tombolenkovac-0.2.4.dist-info/entry_points.txt
tombolenkovac-0.2.4.dist-info/top_level.txt
tombolenkovac-0.2.4.dist-info/RECORD
