Metadata-Version: 2.1
Name: tombolenkovac
Version: 0.2.4
Summary: Create, draw and check tickets for a tombola.
Home-page: 
Download-URL: 
Author: Ondřej Chwiedziuk
Author-email: ondra@chwiedziuk.cz
Keywords: tombola,tickets
License-File: LICENSE
Requires-Dist: fpdf
Requires-Dist: Pillow
Requires-Dist: python-barcode
Requires-Dist: PyPDF2
